{
  "protocol": "hl7_v2",
  "message_type": "ORU^R01",
  "timestamp": "2025-11-22T16:46:14.757638",
  "trigger_event": "R01",
  "segments": [
    {
      "segment": "MSH",
      "fields": [
        {
          "name": "field_separator",
          "position": 1,
          "value": "|"
        },
        {
          "name": "encoding_characters",
          "position": 2,
          "value": "^~\\&"
        },
        {
          "name": "sending_application",
          "position": 3,
          "value": "LIS"
        },
        {
          "name": "sending_facility",
          "position": 4,
          "value": "MedicalCenter"
        },
        {
          "name": "receiving_application",
          "position": 5,
          "value": "CDR"
        },
        {
          "name": "receiving_facility",
          "position": 6,
          "value": "MAINLAB"
        },
        {
          "name": "datetime",
          "position": 7,
          "value": "20251121172614"
        },
        {
          "name": "message_type",
          "position": 9,
          "value": "ORU^R01"
        },
        {
          "name": "message_control_id",
          "position": 10,
          "value": "770923"
        },
        {
          "name": "processing_id",
          "position": 11,
          "value": "P"
        },
        {
          "name": "version_id",
          "position": 12,
          "value": "2.5.1"
        }
      ]
    },
    {
      "segment": "PID",
      "fields": [
        {
          "name": "set_id",
          "position": 1,
          "value": "1"
        },
        {
          "name": "patient_id",
          "position": 3,
          "value": "PAT0SWDUG5L"
        },
        {
          "name": "patient_name",
          "position": 5,
          "value": "Jones^Robert^J"
        },
        {
          "name": "date_of_birth",
          "position": 7,
          "value": "19580710"
        },
        {
          "name": "sex",
          "position": 8,
          "value": "M"
        },
        {
          "name": "address",
          "position": 11,
          "value": "1040 Oak Ave^^Georgetown^GA^16060^USA"
        },
        {
          "name": "phone",
          "position": 13,
          "value": "(758)279-4615"
        },
        {
          "name": "ssn",
          "position": 19,
          "value": "909-72-3543"
        }
      ]
    },
    {
      "segment": "PV1",
      "fields": [
        {
          "name": "set_id",
          "position": 1,
          "value": "1"
        },
        {
          "name": "patient_class",
          "position": 2,
          "value": "R"
        },
        {
          "name": "assigned_location",
          "position": 3,
          "value": "SURG^133^1"
        },
        {
          "name": "attending_doctor",
          "position": 7,
          "value": "84418^Miller^William^MD"
        },
        {
          "name": "visit_number",
          "position": 19,
          "value": "VVFA2N1L9GF"
        },
        {
          "name": "admit_datetime",
          "position": 44,
          "value": "20251105084514"
        }
      ]
    },
    {
      "segment": "OBR",
      "fields": [
        {
          "name": "set_id",
          "position": 1,
          "value": "1"
        },
        {
          "name": "placer_order_number",
          "position": 2,
          "value": "ORDYY3HBTTH9K"
        },
        {
          "name": "filler_order_number",
          "position": 3,
          "value": "FILRQWB9SLO9N"
        },
        {
          "name": "universal_service_id",
          "position": 4,
          "value": "2823-3^Potassium^LN"
        },
        {
          "name": "requested_datetime",
          "position": 7,
          "value": "20251119024714"
        },
        {
          "name": "observation_datetime",
          "position": 14,
          "value": "20251121191014"
        },
        {
          "name": "ordering_provider",
          "position": 16,
          "value": "93071^Jones^Richard^MD"
        },
        {
          "name": "result_status",
          "position": 25,
          "value": "F"
        }
      ]
    },
    {
      "segment": "OBX",
      "fields": [
        {
          "name": "set_id",
          "position": 1,
          "value": "1"
        },
        {
          "name": "value_type",
          "position": 2,
          "value": "NM"
        },
        {
          "name": "observation_identifier",
          "position": 3,
          "value": "4544-3^Hematocrit^LN"
        },
        {
          "name": "observation_value",
          "position": 5,
          "value": "43.1"
        },
        {
          "name": "units",
          "position": 6,
          "value": "%"
        },
        {
          "name": "reference_range",
          "position": 7,
          "value": "36-50"
        },
        {
          "name": "abnormal_flags",
          "position": 8,
          "value": ""
        },
        {
          "name": "observation_result_status",
          "position": 11,
          "value": "F"
        },
        {
          "name": "observation_datetime",
          "position": 14,
          "value": "20251120174514"
        }
      ]
    },
    {
      "segment": "OBX",
      "fields": [
        {
          "name": "set_id",
          "position": 1,
          "value": "2"
        },
        {
          "name": "value_type",
          "position": 2,
          "value": "NM"
        },
        {
          "name": "observation_identifier",
          "position": 3,
          "value": "777-3^Platelet^LN"
        },
        {
          "name": "observation_value",
          "position": 5,
          "value": "231.7"
        },
        {
          "name": "units",
          "position": 6,
          "value": "10*3/uL"
        },
        {
          "name": "reference_range",
          "position": 7,
          "value": "150-400"
        },
        {
          "name": "abnormal_flags",
          "position": 8,
          "value": ""
        },
        {
          "name": "observation_result_status",
          "position": 11,
          "value": "F"
        },
        {
          "name": "observation_datetime",
          "position": 14,
          "value": "20251122055614"
        }
      ]
    },
    {
      "segment": "OBX",
      "fields": [
        {
          "name": "set_id",
          "position": 1,
          "value": "3"
        },
        {
          "name": "value_type",
          "position": 2,
          "value": "NM"
        },
        {
          "name": "observation_identifier",
          "position": 3,
          "value": "4544-3^Hematocrit^LN"
        },
        {
          "name": "observation_value",
          "position": 5,
          "value": "38.3"
        },
        {
          "name": "units",
          "position": 6,
          "value": "%"
        },
        {
          "name": "reference_range",
          "position": 7,
          "value": "36-50"
        },
        {
          "name": "abnormal_flags",
          "position": 8,
          "value": ""
        },
        {
          "name": "observation_result_status",
          "position": 11,
          "value": "F"
        },
        {
          "name": "observation_datetime",
          "position": 14,
          "value": "20251121112214"
        }
      ]
    },
    {
      "segment": "OBR",
      "fields": [
        {
          "name": "set_id",
          "position": 1,
          "value": "2"
        },
        {
          "name": "placer_order_number",
          "position": 2,
          "value": "ORDN1F32L0FI8"
        },
        {
          "name": "filler_order_number",
          "position": 3,
          "value": "FILZ573VF80JG"
        },
        {
          "name": "universal_service_id",
          "position": 4,
          "value": "2951-2^Sodium^LN"
        },
        {
          "name": "requested_datetime",
          "position": 7,
          "value": "20251117203014"
        },
        {
          "name": "observation_datetime",
          "position": 14,
          "value": "20251121032114"
        },
        {
          "name": "ordering_provider",
          "position": 16,
          "value": "23809^Smith^Linda^MD"
        },
        {
          "name": "result_status",
          "position": 25,
          "value": "F"
        }
      ]
    },
    {
      "segment": "OBX",
      "fields": [
        {
          "name": "set_id",
          "position": 1,
          "value": "1"
        },
        {
          "name": "value_type",
          "position": 2,
          "value": "NM"
        },
        {
          "name": "observation_identifier",
          "position": 3,
          "value": "2823-3^Potassium^LN"
        },
        {
          "name": "observation_value",
          "position": 5,
          "value": "4.5"
        },
        {
          "name": "units",
          "position": 6,
          "value": "mEq/L"
        },
        {
          "name": "reference_range",
          "position": 7,
          "value": "3.5-5.1"
        },
        {
          "name": "abnormal_flags",
          "position": 8,
          "value": ""
        },
        {
          "name": "observation_result_status",
          "position": 11,
          "value": "F"
        },
        {
          "name": "observation_datetime",
          "position": 14,
          "value": "20251121141214"
        }
      ]
    },
    {
      "segment": "OBR",
      "fields": [
        {
          "name": "set_id",
          "position": 1,
          "value": "3"
        },
        {
          "name": "placer_order_number",
          "position": 2,
          "value": "ORDBNSG3N0SSQ"
        },
        {
          "name": "filler_order_number",
          "position": 3,
          "value": "FIL98JJ6JAI71"
        },
        {
          "name": "universal_service_id",
          "position": 4,
          "value": "718-7^Hemoglobin^LN"
        },
        {
          "name": "requested_datetime",
          "position": 7,
          "value": "20251121001914"
        },
        {
          "name": "observation_datetime",
          "position": 14,
          "value": "20251121025514"
        },
        {
          "name": "ordering_provider",
          "position": 16,
          "value": "21361^Brown^Patricia^MD"
        },
        {
          "name": "result_status",
          "position": 25,
          "value": "F"
        }
      ]
    },
    {
      "segment": "OBX",
      "fields": [
        {
          "name": "set_id",
          "position": 1,
          "value": "1"
        },
        {
          "name": "value_type",
          "position": 2,
          "value": "NM"
        },
        {
          "name": "observation_identifier",
          "position": 3,
          "value": "2345-7^Glucose^LN"
        },
        {
          "name": "observation_value",
          "position": 5,
          "value": "180.5"
        },
        {
          "name": "units",
          "position": 6,
          "value": "mg/dL"
        },
        {
          "name": "reference_range",
          "position": 7,
          "value": "70-200"
        },
        {
          "name": "abnormal_flags",
          "position": 8,
          "value": ""
        },
        {
          "name": "observation_result_status",
          "position": 11,
          "value": "F"
        },
        {
          "name": "observation_datetime",
          "position": 14,
          "value": "20251121180514"
        }
      ]
    },
    {
      "segment": "OBX",
      "fields": [
        {
          "name": "set_id",
          "position": 1,
          "value": "2"
        },
        {
          "name": "value_type",
          "position": 2,
          "value": "NM"
        },
        {
          "name": "observation_identifier",
          "position": 3,
          "value": "2951-2^Sodium^LN"
        },
        {
          "name": "observation_value",
          "position": 5,
          "value": "143.8"
        },
        {
          "name": "units",
          "position": 6,
          "value": "mEq/L"
        },
        {
          "name": "reference_range",
          "position": 7,
          "value": "136-145"
        },
        {
          "name": "abnormal_flags",
          "position": 8,
          "value": ""
        },
        {
          "name": "observation_result_status",
          "position": 11,
          "value": "F"
        },
        {
          "name": "observation_datetime",
          "position": 14,
          "value": "20251121234514"
        }
      ]
    },
    {
      "segment": "OBR",
      "fields": [
        {
          "name": "set_id",
          "position": 1,
          "value": "4"
        },
        {
          "name": "placer_order_number",
          "position": 2,
          "value": "ORDEUGQV2X2H8"
        },
        {
          "name": "filler_order_number",
          "position": 3,
          "value": "FILV2WV3DYF7B"
        },
        {
          "name": "universal_service_id",
          "position": 4,
          "value": "4544-3^Hematocrit^LN"
        },
        {
          "name": "requested_datetime",
          "position": 7,
          "value": "20251119131414"
        },
        {
          "name": "observation_datetime",
          "position": 14,
          "value": "20251121114514"
        },
        {
          "name": "ordering_provider",
          "position": 16,
          "value": "10773^Hernandez^William^MD"
        },
        {
          "name": "result_status",
          "position": 25,
          "value": "F"
        }
      ]
    },
    {
      "segment": "OBX",
      "fields": [
        {
          "name": "set_id",
          "position": 1,
          "value": "1"
        },
        {
          "name": "value_type",
          "position": 2,
          "value": "NM"
        },
        {
          "name": "observation_identifier",
          "position": 3,
          "value": "2160-0^Creatinine^LN"
        },
        {
          "name": "observation_value",
          "position": 5,
          "value": "0.9"
        },
        {
          "name": "units",
          "position": 6,
          "value": "mg/dL"
        },
        {
          "name": "reference_range",
          "position": 7,
          "value": "0.6-1.5"
        },
        {
          "name": "abnormal_flags",
          "position": 8,
          "value": ""
        },
        {
          "name": "observation_result_status",
          "position": 11,
          "value": "F"
        },
        {
          "name": "observation_datetime",
          "position": 14,
          "value": "20251122134714"
        }
      ]
    }
  ],
  "fields": [],
  "segment_count": 14,
  "hash": "f42b0740269a8d6042c56b99f1b044b671df6d97b7fafd03d32b2bb160c6961a",
  "sample_index": 435
}