{
  "protocol": "hl7_v2",
  "message_type": "ORU^R01",
  "timestamp": "2025-11-22T16:46:14.902620",
  "trigger_event": "R01",
  "segments": [
    {
      "segment": "MSH",
      "fields": [
        {
          "name": "field_separator",
          "position": 1,
          "value": "|"
        },
        {
          "name": "encoding_characters",
          "position": 2,
          "value": "^~\\&"
        },
        {
          "name": "sending_application",
          "position": 3,
          "value": "RIS"
        },
        {
          "name": "sending_facility",
          "position": 4,
          "value": "GeneralHospital"
        },
        {
          "name": "receiving_application",
          "position": 5,
          "value": "EMR"
        },
        {
          "name": "receiving_facility",
          "position": 6,
          "value": "MAINLAB"
        },
        {
          "name": "datetime",
          "position": 7,
          "value": "20251122095614"
        },
        {
          "name": "message_type",
          "position": 9,
          "value": "ORU^R01"
        },
        {
          "name": "message_control_id",
          "position": 10,
          "value": "771258"
        },
        {
          "name": "processing_id",
          "position": 11,
          "value": "P"
        },
        {
          "name": "version_id",
          "position": 12,
          "value": "2.5.1"
        }
      ]
    },
    {
      "segment": "PID",
      "fields": [
        {
          "name": "set_id",
          "position": 1,
          "value": "1"
        },
        {
          "name": "patient_id",
          "position": 3,
          "value": "PAT1S90NX72"
        },
        {
          "name": "patient_name",
          "position": 5,
          "value": "Hernandez^William^A"
        },
        {
          "name": "date_of_birth",
          "position": 7,
          "value": "19780915"
        },
        {
          "name": "sex",
          "position": 8,
          "value": "M"
        },
        {
          "name": "address",
          "position": 11,
          "value": "8721 Park Rd^^Clinton^NY^95511^USA"
        },
        {
          "name": "phone",
          "position": 13,
          "value": "(830)488-4111"
        },
        {
          "name": "ssn",
          "position": 19,
          "value": "806-54-7392"
        }
      ]
    },
    {
      "segment": "PV1",
      "fields": [
        {
          "name": "set_id",
          "position": 1,
          "value": "1"
        },
        {
          "name": "patient_class",
          "position": 2,
          "value": "R"
        },
        {
          "name": "assigned_location",
          "position": 3,
          "value": "ICU^677^4"
        },
        {
          "name": "attending_doctor",
          "position": 7,
          "value": "85593^Rodriguez^Linda^MD"
        },
        {
          "name": "visit_number",
          "position": 19,
          "value": "VEW6XCZ40EQ"
        },
        {
          "name": "admit_datetime",
          "position": 44,
          "value": "20251023074214"
        }
      ]
    },
    {
      "segment": "OBR",
      "fields": [
        {
          "name": "set_id",
          "position": 1,
          "value": "1"
        },
        {
          "name": "placer_order_number",
          "position": 2,
          "value": "ORDGGXM6H2PPX"
        },
        {
          "name": "filler_order_number",
          "position": 3,
          "value": "FILPCH7WJGFBW"
        },
        {
          "name": "universal_service_id",
          "position": 4,
          "value": "4544-3^Hematocrit^LN"
        },
        {
          "name": "requested_datetime",
          "position": 7,
          "value": "20251120214914"
        },
        {
          "name": "observation_datetime",
          "position": 14,
          "value": "20251120173214"
        },
        {
          "name": "ordering_provider",
          "position": 16,
          "value": "44525^Rodriguez^Linda^MD"
        },
        {
          "name": "result_status",
          "position": 25,
          "value": "F"
        }
      ]
    },
    {
      "segment": "OBX",
      "fields": [
        {
          "name": "set_id",
          "position": 1,
          "value": "1"
        },
        {
          "name": "value_type",
          "position": 2,
          "value": "NM"
        },
        {
          "name": "observation_identifier",
          "position": 3,
          "value": "2345-7^Glucose^LN"
        },
        {
          "name": "observation_value",
          "position": 5,
          "value": "170.2"
        },
        {
          "name": "units",
          "position": 6,
          "value": "mg/dL"
        },
        {
          "name": "reference_range",
          "position": 7,
          "value": "70-200"
        },
        {
          "name": "abnormal_flags",
          "position": 8,
          "value": ""
        },
        {
          "name": "observation_result_status",
          "position": 11,
          "value": "F"
        },
        {
          "name": "observation_datetime",
          "position": 14,
          "value": "20251121020014"
        }
      ]
    },
    {
      "segment": "OBR",
      "fields": [
        {
          "name": "set_id",
          "position": 1,
          "value": "2"
        },
        {
          "name": "placer_order_number",
          "position": 2,
          "value": "ORDY3TK0YEZRT"
        },
        {
          "name": "filler_order_number",
          "position": 3,
          "value": "FILKB92XMAXGG"
        },
        {
          "name": "universal_service_id",
          "position": 4,
          "value": "2951-2^Sodium^LN"
        },
        {
          "name": "requested_datetime",
          "position": 7,
          "value": "20251120082714"
        },
        {
          "name": "observation_datetime",
          "position": 14,
          "value": "20251120213714"
        },
        {
          "name": "ordering_provider",
          "position": 16,
          "value": "86492^Hernandez^Jennifer^MD"
        },
        {
          "name": "result_status",
          "position": 25,
          "value": "F"
        }
      ]
    },
    {
      "segment": "OBX",
      "fields": [
        {
          "name": "set_id",
          "position": 1,
          "value": "1"
        },
        {
          "name": "value_type",
          "position": 2,
          "value": "NM"
        },
        {
          "name": "observation_identifier",
          "position": 3,
          "value": "6690-2^WBC^LN"
        },
        {
          "name": "observation_value",
          "position": 5,
          "value": "10.5"
        },
        {
          "name": "units",
          "position": 6,
          "value": "10*3/uL"
        },
        {
          "name": "reference_range",
          "position": 7,
          "value": "4.5-11"
        },
        {
          "name": "abnormal_flags",
          "position": 8,
          "value": ""
        },
        {
          "name": "observation_result_status",
          "position": 11,
          "value": "F"
        },
        {
          "name": "observation_datetime",
          "position": 14,
          "value": "20251120232214"
        }
      ]
    },
    {
      "segment": "OBX",
      "fields": [
        {
          "name": "set_id",
          "position": 1,
          "value": "2"
        },
        {
          "name": "value_type",
          "position": 2,
          "value": "NM"
        },
        {
          "name": "observation_identifier",
          "position": 3,
          "value": "2160-0^Creatinine^LN"
        },
        {
          "name": "observation_value",
          "position": 5,
          "value": "0.7"
        },
        {
          "name": "units",
          "position": 6,
          "value": "mg/dL"
        },
        {
          "name": "reference_range",
          "position": 7,
          "value": "0.6-1.5"
        },
        {
          "name": "abnormal_flags",
          "position": 8,
          "value": ""
        },
        {
          "name": "observation_result_status",
          "position": 11,
          "value": "F"
        },
        {
          "name": "observation_datetime",
          "position": 14,
          "value": "20251121164314"
        }
      ]
    },
    {
      "segment": "OBX",
      "fields": [
        {
          "name": "set_id",
          "position": 1,
          "value": "3"
        },
        {
          "name": "value_type",
          "position": 2,
          "value": "NM"
        },
        {
          "name": "observation_identifier",
          "position": 3,
          "value": "2951-2^Sodium^LN"
        },
        {
          "name": "observation_value",
          "position": 5,
          "value": "138.3"
        },
        {
          "name": "units",
          "position": 6,
          "value": "mEq/L"
        },
        {
          "name": "reference_range",
          "position": 7,
          "value": "136-145"
        },
        {
          "name": "abnormal_flags",
          "position": 8,
          "value": ""
        },
        {
          "name": "observation_result_status",
          "position": 11,
          "value": "F"
        },
        {
          "name": "observation_datetime",
          "position": 14,
          "value": "20251121203614"
        }
      ]
    }
  ],
  "fields": [],
  "segment_count": 9,
  "hash": "9016302e75951c153343a014f9dc377d595be3e4035003e2dc83762d6a254c8a",
  "sample_index": 770
}