{
  "protocol": "hl7_v2",
  "message_type": "ORU^R01",
  "timestamp": "2025-11-22T16:46:14.814034",
  "trigger_event": "R01",
  "segments": [
    {
      "segment": "MSH",
      "fields": [
        {
          "name": "field_separator",
          "position": 1,
          "value": "|"
        },
        {
          "name": "encoding_characters",
          "position": 2,
          "value": "^~\\&"
        },
        {
          "name": "sending_application",
          "position": 3,
          "value": "LAB"
        },
        {
          "name": "sending_facility",
          "position": 4,
          "value": "RegionalMedical"
        },
        {
          "name": "receiving_application",
          "position": 5,
          "value": "HIE"
        },
        {
          "name": "receiving_facility",
          "position": 6,
          "value": "MAINLAB"
        },
        {
          "name": "datetime",
          "position": 7,
          "value": "20251121170314"
        },
        {
          "name": "message_type",
          "position": 9,
          "value": "ORU^R01"
        },
        {
          "name": "message_control_id",
          "position": 10,
          "value": "771054"
        },
        {
          "name": "processing_id",
          "position": 11,
          "value": "P"
        },
        {
          "name": "version_id",
          "position": 12,
          "value": "2.5.1"
        }
      ]
    },
    {
      "segment": "PID",
      "fields": [
        {
          "name": "set_id",
          "position": 1,
          "value": "1"
        },
        {
          "name": "patient_id",
          "position": 3,
          "value": "PATEAJEHFA6"
        },
        {
          "name": "patient_name",
          "position": 5,
          "value": "Johnson^Joseph^J"
        },
        {
          "name": "date_of_birth",
          "position": 7,
          "value": "19610203"
        },
        {
          "name": "sex",
          "position": 8,
          "value": "F"
        },
        {
          "name": "address",
          "position": 11,
          "value": "7275 Lincoln Ave^^Clinton^OH^71434^USA"
        },
        {
          "name": "phone",
          "position": 13,
          "value": "(522)698-4595"
        },
        {
          "name": "ssn",
          "position": 19,
          "value": "273-99-6188"
        }
      ]
    },
    {
      "segment": "PV1",
      "fields": [
        {
          "name": "set_id",
          "position": 1,
          "value": "1"
        },
        {
          "name": "patient_class",
          "position": 2,
          "value": "P"
        },
        {
          "name": "assigned_location",
          "position": 3,
          "value": "OBS^257^3"
        },
        {
          "name": "attending_doctor",
          "position": 7,
          "value": "62233^Johnson^Susan^MD"
        },
        {
          "name": "visit_number",
          "position": 19,
          "value": "VZJMPQGDKF0"
        },
        {
          "name": "admit_datetime",
          "position": 44,
          "value": "20251114153214"
        }
      ]
    },
    {
      "segment": "OBR",
      "fields": [
        {
          "name": "set_id",
          "position": 1,
          "value": "1"
        },
        {
          "name": "placer_order_number",
          "position": 2,
          "value": "ORDZBLN9EQRJO"
        },
        {
          "name": "filler_order_number",
          "position": 3,
          "value": "FIL4RLE9GGZ64"
        },
        {
          "name": "universal_service_id",
          "position": 4,
          "value": "2160-0^Creatinine^LN"
        },
        {
          "name": "requested_datetime",
          "position": 7,
          "value": "20251117144814"
        },
        {
          "name": "observation_datetime",
          "position": 14,
          "value": "20251122120714"
        },
        {
          "name": "ordering_provider",
          "position": 16,
          "value": "76110^Brown^John^MD"
        },
        {
          "name": "result_status",
          "position": 25,
          "value": "F"
        }
      ]
    },
    {
      "segment": "OBX",
      "fields": [
        {
          "name": "set_id",
          "position": 1,
          "value": "1"
        },
        {
          "name": "value_type",
          "position": 2,
          "value": "NM"
        },
        {
          "name": "observation_identifier",
          "position": 3,
          "value": "3094-0^BUN^LN"
        },
        {
          "name": "observation_value",
          "position": 5,
          "value": "9.6"
        },
        {
          "name": "units",
          "position": 6,
          "value": "mg/dL"
        },
        {
          "name": "reference_range",
          "position": 7,
          "value": "7-25"
        },
        {
          "name": "abnormal_flags",
          "position": 8,
          "value": ""
        },
        {
          "name": "observation_result_status",
          "position": 11,
          "value": "F"
        },
        {
          "name": "observation_datetime",
          "position": 14,
          "value": "20251122095014"
        }
      ]
    },
    {
      "segment": "OBX",
      "fields": [
        {
          "name": "set_id",
          "position": 1,
          "value": "2"
        },
        {
          "name": "value_type",
          "position": 2,
          "value": "NM"
        },
        {
          "name": "observation_identifier",
          "position": 3,
          "value": "6690-2^WBC^LN"
        },
        {
          "name": "observation_value",
          "position": 5,
          "value": "4.7"
        },
        {
          "name": "units",
          "position": 6,
          "value": "10*3/uL"
        },
        {
          "name": "reference_range",
          "position": 7,
          "value": "4.5-11"
        },
        {
          "name": "abnormal_flags",
          "position": 8,
          "value": ""
        },
        {
          "name": "observation_result_status",
          "position": 11,
          "value": "F"
        },
        {
          "name": "observation_datetime",
          "position": 14,
          "value": "20251120184414"
        }
      ]
    },
    {
      "segment": "OBX",
      "fields": [
        {
          "name": "set_id",
          "position": 1,
          "value": "3"
        },
        {
          "name": "value_type",
          "position": 2,
          "value": "NM"
        },
        {
          "name": "observation_identifier",
          "position": 3,
          "value": "2951-2^Sodium^LN"
        },
        {
          "name": "observation_value",
          "position": 5,
          "value": "141.8"
        },
        {
          "name": "units",
          "position": 6,
          "value": "mEq/L"
        },
        {
          "name": "reference_range",
          "position": 7,
          "value": "136-145"
        },
        {
          "name": "abnormal_flags",
          "position": 8,
          "value": ""
        },
        {
          "name": "observation_result_status",
          "position": 11,
          "value": "F"
        },
        {
          "name": "observation_datetime",
          "position": 14,
          "value": "20251121161514"
        }
      ]
    },
    {
      "segment": "OBR",
      "fields": [
        {
          "name": "set_id",
          "position": 1,
          "value": "2"
        },
        {
          "name": "placer_order_number",
          "position": 2,
          "value": "ORDFKBFQ1MENE"
        },
        {
          "name": "filler_order_number",
          "position": 3,
          "value": "FILPYF0LNWIN5"
        },
        {
          "name": "universal_service_id",
          "position": 4,
          "value": "3094-0^BUN^LN"
        },
        {
          "name": "requested_datetime",
          "position": 7,
          "value": "20251115001914"
        },
        {
          "name": "observation_datetime",
          "position": 14,
          "value": "20251121170114"
        },
        {
          "name": "ordering_provider",
          "position": 16,
          "value": "48788^Rodriguez^Susan^MD"
        },
        {
          "name": "result_status",
          "position": 25,
          "value": "F"
        }
      ]
    },
    {
      "segment": "OBX",
      "fields": [
        {
          "name": "set_id",
          "position": 1,
          "value": "1"
        },
        {
          "name": "value_type",
          "position": 2,
          "value": "NM"
        },
        {
          "name": "observation_identifier",
          "position": 3,
          "value": "718-7^Hemoglobin^LN"
        },
        {
          "name": "observation_value",
          "position": 5,
          "value": "15.6"
        },
        {
          "name": "units",
          "position": 6,
          "value": "g/dL"
        },
        {
          "name": "reference_range",
          "position": 7,
          "value": "12-17"
        },
        {
          "name": "abnormal_flags",
          "position": 8,
          "value": ""
        },
        {
          "name": "observation_result_status",
          "position": 11,
          "value": "F"
        },
        {
          "name": "observation_datetime",
          "position": 14,
          "value": "20251122121314"
        }
      ]
    },
    {
      "segment": "OBX",
      "fields": [
        {
          "name": "set_id",
          "position": 1,
          "value": "2"
        },
        {
          "name": "value_type",
          "position": 2,
          "value": "NM"
        },
        {
          "name": "observation_identifier",
          "position": 3,
          "value": "2345-7^Glucose^LN"
        },
        {
          "name": "observation_value",
          "position": 5,
          "value": "199.0"
        },
        {
          "name": "units",
          "position": 6,
          "value": "mg/dL"
        },
        {
          "name": "reference_range",
          "position": 7,
          "value": "70-200"
        },
        {
          "name": "abnormal_flags",
          "position": 8,
          "value": ""
        },
        {
          "name": "observation_result_status",
          "position": 11,
          "value": "F"
        },
        {
          "name": "observation_datetime",
          "position": 14,
          "value": "20251120205314"
        }
      ]
    }
  ],
  "fields": [],
  "segment_count": 10,
  "hash": "7da2eb1296ccfd0ac524a904e0199ea43fed926d7eb0d8ae5310d1ee51d6a850",
  "sample_index": 566
}