{
  "protocol": "hl7_v2",
  "message_type": "ORU^R01",
  "timestamp": "2025-11-22T16:46:14.845543",
  "trigger_event": "R01",
  "segments": [
    {
      "segment": "MSH",
      "fields": [
        {
          "name": "field_separator",
          "position": 1,
          "value": "|"
        },
        {
          "name": "encoding_characters",
          "position": 2,
          "value": "^~\\&"
        },
        {
          "name": "sending_application",
          "position": 3,
          "value": "HIS"
        },
        {
          "name": "sending_facility",
          "position": 4,
          "value": "MedicalCenter"
        },
        {
          "name": "receiving_application",
          "position": 5,
          "value": "EMR"
        },
        {
          "name": "receiving_facility",
          "position": 6,
          "value": "MAINLAB"
        },
        {
          "name": "datetime",
          "position": 7,
          "value": "20251122023414"
        },
        {
          "name": "message_type",
          "position": 9,
          "value": "ORU^R01"
        },
        {
          "name": "message_control_id",
          "position": 10,
          "value": "771126"
        },
        {
          "name": "processing_id",
          "position": 11,
          "value": "P"
        },
        {
          "name": "version_id",
          "position": 12,
          "value": "2.5.1"
        }
      ]
    },
    {
      "segment": "PID",
      "fields": [
        {
          "name": "set_id",
          "position": 1,
          "value": "1"
        },
        {
          "name": "patient_id",
          "position": 3,
          "value": "PATG5BI1IWK"
        },
        {
          "name": "patient_name",
          "position": 5,
          "value": "Hernandez^Susan^R"
        },
        {
          "name": "date_of_birth",
          "position": 7,
          "value": "19861102"
        },
        {
          "name": "sex",
          "position": 8,
          "value": "F"
        },
        {
          "name": "address",
          "position": 11,
          "value": "613 Washington Blvd^^Salem^NY^35950^USA"
        },
        {
          "name": "phone",
          "position": 13,
          "value": "(711)270-9784"
        },
        {
          "name": "ssn",
          "position": 19,
          "value": "489-55-9286"
        }
      ]
    },
    {
      "segment": "PV1",
      "fields": [
        {
          "name": "set_id",
          "position": 1,
          "value": "1"
        },
        {
          "name": "patient_class",
          "position": 2,
          "value": "O"
        },
        {
          "name": "assigned_location",
          "position": 3,
          "value": "MED^929^2"
        },
        {
          "name": "attending_doctor",
          "position": 7,
          "value": "61303^Anderson^Robert^MD"
        },
        {
          "name": "visit_number",
          "position": 19,
          "value": "VCE5903KLTD"
        },
        {
          "name": "admit_datetime",
          "position": 44,
          "value": "20251111110314"
        }
      ]
    },
    {
      "segment": "OBR",
      "fields": [
        {
          "name": "set_id",
          "position": 1,
          "value": "1"
        },
        {
          "name": "placer_order_number",
          "position": 2,
          "value": "ORDC3PVSPL4KX"
        },
        {
          "name": "filler_order_number",
          "position": 3,
          "value": "FILB4OF37CQRW"
        },
        {
          "name": "universal_service_id",
          "position": 4,
          "value": "6690-2^WBC^LN"
        },
        {
          "name": "requested_datetime",
          "position": 7,
          "value": "20251117230514"
        },
        {
          "name": "observation_datetime",
          "position": 14,
          "value": "20251121204714"
        },
        {
          "name": "ordering_provider",
          "position": 16,
          "value": "33312^Brown^Joseph^MD"
        },
        {
          "name": "result_status",
          "position": 25,
          "value": "F"
        }
      ]
    },
    {
      "segment": "OBX",
      "fields": [
        {
          "name": "set_id",
          "position": 1,
          "value": "1"
        },
        {
          "name": "value_type",
          "position": 2,
          "value": "NM"
        },
        {
          "name": "observation_identifier",
          "position": 3,
          "value": "2345-7^Glucose^LN"
        },
        {
          "name": "observation_value",
          "position": 5,
          "value": "161.1"
        },
        {
          "name": "units",
          "position": 6,
          "value": "mg/dL"
        },
        {
          "name": "reference_range",
          "position": 7,
          "value": "70-200"
        },
        {
          "name": "abnormal_flags",
          "position": 8,
          "value": ""
        },
        {
          "name": "observation_result_status",
          "position": 11,
          "value": "F"
        },
        {
          "name": "observation_datetime",
          "position": 14,
          "value": "20251121014514"
        }
      ]
    },
    {
      "segment": "OBX",
      "fields": [
        {
          "name": "set_id",
          "position": 1,
          "value": "2"
        },
        {
          "name": "value_type",
          "position": 2,
          "value": "NM"
        },
        {
          "name": "observation_identifier",
          "position": 3,
          "value": "6690-2^WBC^LN"
        },
        {
          "name": "observation_value",
          "position": 5,
          "value": "10.8"
        },
        {
          "name": "units",
          "position": 6,
          "value": "10*3/uL"
        },
        {
          "name": "reference_range",
          "position": 7,
          "value": "4.5-11"
        },
        {
          "name": "abnormal_flags",
          "position": 8,
          "value": ""
        },
        {
          "name": "observation_result_status",
          "position": 11,
          "value": "F"
        },
        {
          "name": "observation_datetime",
          "position": 14,
          "value": "20251122031914"
        }
      ]
    }
  ],
  "fields": [],
  "segment_count": 6,
  "hash": "5d407526512b1b89fc4a352becb66148eccfbfd897b2a551a0125ff36f020e77",
  "sample_index": 638
}