{
  "program_id": "SECX984",
  "domain": "finance",
  "program_type": "archival",
  "author": "T. DAVIS",
  "lines_of_code": 196,
  "complexity_level": "medium",
  "complexity_score": 0.487,
  "files_used": 2,
  "verbs_used": 12,
  "has_indexed_files": false,
  "has_packed_decimal": true,
  "has_binary_fields": true,
  "has_perform_loops": true,
  "has_evaluate": false,
  "has_call_statements": false,
  "generated_date": "2026-01-10T09:18:36.837941",
  "hash": "f6e2ffa5ee1b1c686a3263e572dfce7b"
}