{
  "program_id": "SKUA953",
  "domain": "retail",
  "program_type": "audit_trail",
  "author": "T. DAVIS",
  "lines_of_code": 196,
  "complexity_level": "medium",
  "complexity_score": 0.487,
  "files_used": 2,
  "verbs_used": 12,
  "has_indexed_files": false,
  "has_packed_decimal": true,
  "has_binary_fields": true,
  "has_perform_loops": true,
  "has_evaluate": false,
  "has_call_statements": false,
  "generated_date": "2026-01-10T09:18:36.836623",
  "hash": "718d5a431f90a78ef54950345b34a6d2"
}