{
  "protocol": "modbus",
  "message_hex": "a60400000013f10310f914ba92cdd142e1bba0bf2ad3e68615",
  "message_bytes": [
    166,
    4,
    0,
    0,
    0,
    19,
    241,
    3,
    16,
    249,
    20,
    186,
    146,
    205,
    209,
    66,
    225,
    187,
    160,
    191,
    42,
    211,
    230,
    134,
    21
  ],
  "tags": [
    "B-FIELD",
    "I-FIELD",
    "B-FIELD",
    "I-FIELD",
    "B-LENGTH",
    "I-LENGTH",
    "B-FIELD",
    "B-FIELD",
    "B-FIELD",
    "B-FIELD",
    "I-FIELD",
    "I-FIELD",
    "I-FIELD",
    "I-FIELD",
    "I-FIELD",
    "I-FIELD",
    "I-FIELD",
    "I-FIELD",
    "I-FIELD",
    "I-FIELD",
    "I-FIELD",
    "I-FIELD",
    "I-FIELD",
    "I-FIELD",
    "I-FIELD"
  ],
  "length": 25,
  "fields": [
    {
      "name": "transaction_id",
      "offset": 0,
      "length": 2,
      "value": 42500
    },
    {
      "name": "protocol_id",
      "offset": 2,
      "length": 2,
      "value": 0
    },
    {
      "name": "length",
      "offset": 4,
      "length": 2,
      "value": 19
    },
    {
      "name": "unit_id",
      "offset": 6,
      "length": 1,
      "value": 241
    },
    {
      "name": "function_code",
      "offset": 7,
      "length": 1,
      "value": 3
    },
    {
      "name": "byte_count",
      "offset": 8,
      "length": 1,
      "value": 16
    },
    {
      "name": "register_values",
      "offset": 9,
      "length": 16,
      "value": "f914ba92cdd142e1bba0bf2ad3e68615"
    }
  ],
  "hash": "04b52f1868c34279701aa3c0ebde1275b934e5a504059badc157d3041a32bc5a"
}