{
  "protocol": "modbus",
  "message_hex": "a45e00000007c101048df87a8c",
  "message_bytes": [
    164,
    94,
    0,
    0,
    0,
    7,
    193,
    1,
    4,
    141,
    248,
    122,
    140
  ],
  "tags": [
    "B-FIELD",
    "I-FIELD",
    "B-FIELD",
    "I-FIELD",
    "B-LENGTH",
    "I-LENGTH",
    "B-FIELD",
    "B-FIELD",
    "B-FIELD",
    "B-FIELD",
    "I-FIELD",
    "I-FIELD",
    "I-FIELD"
  ],
  "length": 13,
  "fields": [
    {
      "name": "transaction_id",
      "offset": 0,
      "length": 2,
      "value": 42078
    },
    {
      "name": "protocol_id",
      "offset": 2,
      "length": 2,
      "value": 0
    },
    {
      "name": "length",
      "offset": 4,
      "length": 2,
      "value": 7
    },
    {
      "name": "unit_id",
      "offset": 6,
      "length": 1,
      "value": 193
    },
    {
      "name": "function_code",
      "offset": 7,
      "length": 1,
      "value": 1
    },
    {
      "name": "byte_count",
      "offset": 8,
      "length": 1,
      "value": 4
    },
    {
      "name": "coil_status",
      "offset": 9,
      "length": 4,
      "value": "8df87a8c"
    }
  ],
  "hash": "15c8e056c891d3950850521507fb777bd19ff9b4473082f3bfa46d9ef8e67be0"
}