{
  "protocol": "modbus",
  "message_hex": "a636000000067906a256d485",
  "message_bytes": [
    166,
    54,
    0,
    0,
    0,
    6,
    121,
    6,
    162,
    86,
    212,
    133
  ],
  "tags": [
    "B-FIELD",
    "I-FIELD",
    "B-FIELD",
    "I-FIELD",
    "B-LENGTH",
    "I-LENGTH",
    "B-FIELD",
    "B-FIELD",
    "B-FIELD",
    "I-FIELD",
    "B-FIELD",
    "I-FIELD"
  ],
  "length": 12,
  "fields": [
    {
      "name": "transaction_id",
      "offset": 0,
      "length": 2,
      "value": 42550
    },
    {
      "name": "protocol_id",
      "offset": 2,
      "length": 2,
      "value": 0
    },
    {
      "name": "length",
      "offset": 4,
      "length": 2,
      "value": 6
    },
    {
      "name": "unit_id",
      "offset": 6,
      "length": 1,
      "value": 121
    },
    {
      "name": "function_code",
      "offset": 7,
      "length": 1,
      "value": 6
    },
    {
      "name": "register_address",
      "offset": 8,
      "length": 2,
      "value": 41558
    },
    {
      "name": "register_value",
      "offset": 10,
      "length": 2,
      "value": 54405
    }
  ],
  "hash": "35d100b30fe0c9063507b50159642dcb760c09e18ce20e3de60404e2dd3a8a2b"
}